{"box_data": [{"position": {"minX": 218.5, "minY": 101.5625, "maxX": 279.5, "maxY": 139.25}, "class_id": 16, "box_caption": "sheep 0.595", "scores": {"class_score": 0.59521484375}, "domain": "pixel"}, {"position": {"minX": 382.75, "minY": 102.75, "maxX": 410.25, "maxY": 137.0}, "class_id": 16, "box_caption": "sheep 0.297", "scores": {"class_score": 0.296630859375}, "domain": "pixel"}, {"position": {"minX": 220.125, "minY": 96.125, "maxX": 279.0, "maxY": 139.125}, "class_id": 9, "box_caption": "cow 0.115", "scores": {"class_score": 0.11492919921875}, "domain": "pixel"}, {"position": {"minX": 218.875, "minY": 95.625, "maxX": 263.25, "maxY": 135.625}, "class_id": 16, "box_caption": "sheep 0.085", "scores": {"class_score": 0.0853271484375}, "domain": "pixel"}, {"position": {"minX": 384.0, "minY": 102.625, "maxX": 411.5, "maxY": 136.875}, "class_id": 9, "box_caption": "cow 0.076", "scores": {"class_score": 0.07635498046875}, "domain": "pixel"}, {"position": {"minX": 213.75, "minY": 90.625, "maxX": 291.0, "maxY": 136.75}, "class_id": 16, "box_caption": "sheep 0.056", "scores": {"class_score": 0.056365966796875}, "domain": "pixel"}, {"position": {"minX": 218.5, "minY": 101.5625, "maxX": 279.5, "maxY": 139.25}, "class_id": 11, "box_caption": "dog 0.043", "scores": {"class_score": 0.043212890625}, "domain": "pixel"}, {"position": {"minX": 377.75, "minY": 98.6875, "maxX": 415.75, "maxY": 130.5}, "class_id": 16, "box_caption": "sheep 0.027", "scores": {"class_score": 0.027435302734375}, "domain": "pixel"}, {"position": {"minX": 231.0, "minY": 97.6875, "maxX": 269.25, "maxY": 140.75}, "class_id": 16, "box_caption": "sheep 0.027", "scores": {"class_score": 0.0273590087890625}, "domain": "pixel"}, {"position": {"minX": 220.625, "minY": 97.25, "maxX": 280.0, "maxY": 140.5}, "class_id": 14, "box_caption": "person 0.026", "scores": {"class_score": 0.0256500244140625}, "domain": "pixel"}, {"position": {"minX": 382.75, "minY": 102.75, "maxX": 410.25, "maxY": 137.0}, "class_id": 14, "box_caption": "person 0.023", "scores": {"class_score": 0.0228729248046875}, "domain": "pixel"}, {"position": {"minX": 220.625, "minY": 97.25, "maxX": 280.0, "maxY": 140.5}, "class_id": 2, "box_caption": "bird 0.022", "scores": {"class_score": 0.0224151611328125}, "domain": "pixel"}, {"position": {"minX": 217.875, "minY": 96.875, "maxX": 280.0, "maxY": 137.375}, "class_id": 7, "box_caption": "cat 0.019", "scores": {"class_score": 0.01898193359375}, "domain": "pixel"}, {"position": {"minX": 220.75, "minY": 99.5, "maxX": 282.5, "maxY": 138.75}, "class_id": 12, "box_caption": "horse 0.019", "scores": {"class_score": 0.0186004638671875}, "domain": "pixel"}, {"position": {"minX": 382.75, "minY": 102.75, "maxX": 410.25, "maxY": 137.0}, "class_id": 2, "box_caption": "bird 0.018", "scores": {"class_score": 0.018157958984375}, "domain": "pixel"}, {"position": {"minX": 220.75, "minY": 99.5, "maxX": 282.5, "maxY": 138.75}, "class_id": 4, "box_caption": "bottle 0.018", "scores": {"class_score": 0.017730712890625}, "domain": "pixel"}, {"position": {"minX": 53.34375, "minY": 104.125, "maxX": 68.5, "maxY": 115.375}, "class_id": 16, "box_caption": "sheep 0.018", "scores": {"class_score": 0.0176849365234375}, "domain": "pixel"}, {"position": {"minX": 380.5, "minY": 102.5, "maxX": 411.5, "maxY": 136.5}, "class_id": 12, "box_caption": "horse 0.017", "scores": {"class_score": 0.0172271728515625}, "domain": "pixel"}, {"position": {"minX": 236.125, "minY": 99.4375, "maxX": 292.5, "maxY": 139.75}, "class_id": 16, "box_caption": "sheep 0.017", "scores": {"class_score": 0.0167083740234375}, "domain": "pixel"}, {"position": {"minX": 382.75, "minY": 102.75, "maxX": 410.25, "maxY": 137.0}, "class_id": 11, "box_caption": "dog 0.017", "scores": {"class_score": 0.016693115234375}, "domain": "pixel"}, {"position": {"minX": 51.5625, "minY": 106.375, "maxX": 71.4375, "maxY": 113.625}, "class_id": 16, "box_caption": "sheep 0.015", "scores": {"class_score": 0.0152130126953125}, "domain": "pixel"}, {"position": {"minX": 238.875, "minY": 102.1875, "maxX": 275.0, "maxY": 138.25}, "class_id": 16, "box_caption": "sheep 0.014", "scores": {"class_score": 0.0141448974609375}, "domain": "pixel"}, {"position": {"minX": 220.625, "minY": 97.25, "maxX": 280.0, "maxY": 140.5}, "class_id": 8, "box_caption": "chair 0.014", "scores": {"class_score": 0.01375579833984375}, "domain": "pixel"}, {"position": {"minX": 380.5, "minY": 102.5, "maxX": 411.5, "maxY": 136.5}, "class_id": 4, "box_caption": "bottle 0.011", "scores": {"class_score": 0.01148223876953125}, "domain": "pixel"}, {"position": {"minX": 220.125, "minY": 96.125, "maxX": 279.0, "maxY": 139.125}, "class_id": 13, "box_caption": "motorbike 0.011", "scores": {"class_score": 0.01119232177734375}, "domain": "pixel"}, {"position": {"minX": 218.125, "minY": 99.8125, "maxX": 248.875, "maxY": 130.875}, "class_id": 16, "box_caption": "sheep 0.011", "scores": {"class_score": 0.0105438232421875}, "domain": "pixel"}, {"position": {"minX": 218.5, "minY": 101.5625, "maxX": 279.5, "maxY": 139.25}, "class_id": 3, "box_caption": "boat 0.010", "scores": {"class_score": 0.0103607177734375}, "domain": "pixel"}, {"position": {"minX": 53.3125, "minY": 106.1875, "maxX": 66.5625, "maxY": 118.0625}, "class_id": 16, "box_caption": "sheep 0.010", "scores": {"class_score": 0.01035308837890625}, "domain": "pixel"}, {"position": {"minX": 220.75, "minY": 95.125, "maxX": 275.25, "maxY": 141.75}, "class_id": 5, "box_caption": "bus 0.010", "scores": {"class_score": 0.01018524169921875}, "domain": "pixel"}, {"position": {"minX": 384.0, "minY": 102.625, "maxX": 411.5, "maxY": 136.875}, "class_id": 3, "box_caption": "boat 0.010", "scores": {"class_score": 0.00984954833984375}, "domain": "pixel"}, {"position": {"minX": 220.75, "minY": 99.5, "maxX": 282.5, "maxY": 138.75}, "class_id": 0, "box_caption": "aeroplane 0.010", "scores": {"class_score": 0.0098419189453125}, "domain": "pixel"}, {"position": {"minX": 383.5, "minY": 116.0625, "maxX": 408.5, "maxY": 135.5}, "class_id": 16, "box_caption": "sheep 0.010", "scores": {"class_score": 0.00975799560546875}, "domain": "pixel"}, {"position": {"minX": 382.75, "minY": 102.75, "maxX": 410.25, "maxY": 137.0}, "class_id": 7, "box_caption": "cat 0.010", "scores": {"class_score": 0.00970458984375}, "domain": "pixel"}, {"position": {"minX": 53.5, "minY": 109.125, "maxX": 69.5, "maxY": 114.625}, "class_id": 16, "box_caption": "sheep 0.009", "scores": {"class_score": 0.00917816162109375}, "domain": "pixel"}, {"position": {"minX": 219.75, "minY": 98.0625, "maxX": 283.0, "maxY": 136.625}, "class_id": 15, "box_caption": "pottedplant 0.009", "scores": {"class_score": 0.008758544921875}, "domain": "pixel"}, {"position": {"minX": 217.5, "minY": 96.25, "maxX": 261.25, "maxY": 130.5}, "class_id": 9, "box_caption": "cow 0.009", "scores": {"class_score": 0.0087127685546875}, "domain": "pixel"}, {"position": {"minX": 220.25, "minY": 96.1875, "maxX": 280.25, "maxY": 135.625}, "class_id": 6, "box_caption": "car 0.009", "scores": {"class_score": 0.00855255126953125}, "domain": "pixel"}, {"position": {"minX": 384.0, "minY": 102.25, "maxX": 412.5, "maxY": 124.75}, "class_id": 16, "box_caption": "sheep 0.008", "scores": {"class_score": 0.00836944580078125}, "domain": "pixel"}, {"position": {"minX": 377.75, "minY": 98.6875, "maxX": 415.75, "maxY": 130.5}, "class_id": 9, "box_caption": "cow 0.008", "scores": {"class_score": 0.0077972412109375}, "domain": "pixel"}, {"position": {"minX": 383.5, "minY": 102.625, "maxX": 415.0, "maxY": 136.125}, "class_id": 5, "box_caption": "bus 0.008", "scores": {"class_score": 0.00768280029296875}, "domain": "pixel"}, {"position": {"minX": 219.75, "minY": 96.5, "maxX": 280.25, "maxY": 137.5}, "class_id": 18, "box_caption": "train 0.007", "scores": {"class_score": 0.007396697998046875}, "domain": "pixel"}, {"position": {"minX": 380.5, "minY": 102.5, "maxX": 411.5, "maxY": 136.5}, "class_id": 0, "box_caption": "aeroplane 0.007", "scores": {"class_score": 0.007080078125}, "domain": "pixel"}, {"position": {"minX": 383.0, "minY": 115.25, "maxX": 409.0, "maxY": 136.125}, "class_id": 9, "box_caption": "cow 0.007", "scores": {"class_score": 0.006961822509765625}, "domain": "pixel"}, {"position": {"minX": 218.5, "minY": 101.5625, "maxX": 279.5, "maxY": 139.25}, "class_id": 1, "box_caption": "bicycle 0.007", "scores": {"class_score": 0.006694793701171875}, "domain": "pixel"}, {"position": {"minX": 231.5, "minY": 106.375, "maxX": 284.5, "maxY": 144.75}, "class_id": 16, "box_caption": "sheep 0.006", "scores": {"class_score": 0.006488800048828125}, "domain": "pixel"}, {"position": {"minX": 382.75, "minY": 102.75, "maxX": 410.25, "maxY": 137.0}, "class_id": 8, "box_caption": "chair 0.006", "scores": {"class_score": 0.006107330322265625}, "domain": "pixel"}, {"position": {"minX": 380.5, "minY": 102.5, "maxX": 411.5, "maxY": 136.5}, "class_id": 13, "box_caption": "motorbike 0.006", "scores": {"class_score": 0.00577545166015625}, "domain": "pixel"}, {"position": {"minX": 218.875, "minY": 95.625, "maxX": 263.25, "maxY": 135.625}, "class_id": 12, "box_caption": "horse 0.006", "scores": {"class_score": 0.00568389892578125}, "domain": "pixel"}, {"position": {"minX": 77.0, "minY": 64.125, "maxX": 95.5, "maxY": 76.125}, "class_id": 16, "box_caption": "sheep 0.005", "scores": {"class_score": 0.00514984130859375}, "domain": "pixel"}, {"position": {"minX": 383.5, "minY": 105.625, "maxX": 413.5, "maxY": 135.125}, "class_id": 15, "box_caption": "pottedplant 0.005", "scores": {"class_score": 0.00504302978515625}, "domain": "pixel"}, {"position": {"minX": 382.75, "minY": 102.75, "maxX": 410.25, "maxY": 137.0}, "class_id": 6, "box_caption": "car 0.005", "scores": {"class_score": 0.005035400390625}, "domain": "pixel"}, {"position": {"minX": 382.75, "minY": 102.75, "maxX": 410.25, "maxY": 137.0}, "class_id": 18, "box_caption": "train 0.005", "scores": {"class_score": 0.004978179931640625}, "domain": "pixel"}, {"position": {"minX": 220.25, "minY": 93.25, "maxX": 278.5, "maxY": 140.875}, "class_id": 17, "box_caption": "sofa 0.005", "scores": {"class_score": 0.004955291748046875}, "domain": "pixel"}, {"position": {"minX": 225.75, "minY": 99.6875, "maxX": 263.75, "maxY": 136.625}, "class_id": 2, "box_caption": "bird 0.005", "scores": {"class_score": 0.004894256591796875}, "domain": "pixel"}, {"position": {"minX": 153.75, "minY": 127.75, "maxX": 176.0, "maxY": 139.0}, "class_id": 16, "box_caption": "sheep 0.005", "scores": {"class_score": 0.004848480224609375}, "domain": "pixel"}, {"position": {"minX": 220.125, "minY": 96.125, "maxX": 279.0, "maxY": 139.125}, "class_id": 10, "box_caption": "diningtable 0.005", "scores": {"class_score": 0.004596710205078125}, "domain": "pixel"}, {"position": {"minX": 48.5625, "minY": 100.5, "maxX": 67.6875, "maxY": 113.875}, "class_id": 16, "box_caption": "sheep 0.004", "scores": {"class_score": 0.00446319580078125}, "domain": "pixel"}, {"position": {"minX": 51.8125, "minY": 106.375, "maxX": 69.375, "maxY": 114.0}, "class_id": 9, "box_caption": "cow 0.004", "scores": {"class_score": 0.004459381103515625}, "domain": "pixel"}, {"position": {"minX": 78.1875, "minY": 68.0, "maxX": 97.5625, "maxY": 73.0}, "class_id": 16, "box_caption": "sheep 0.004", "scores": {"class_score": 0.0043487548828125}, "domain": "pixel"}, {"position": {"minX": 218.5, "minY": 101.5625, "maxX": 279.5, "maxY": 139.25}, "class_id": 19, "box_caption": "tvmonitor 0.004", "scores": {"class_score": 0.0040435791015625}, "domain": "pixel"}, {"position": {"minX": 325.5, "minY": 154.375, "maxX": 348.0, "maxY": 171.125}, "class_id": 16, "box_caption": "sheep 0.004", "scores": {"class_score": 0.003902435302734375}, "domain": "pixel"}, {"position": {"minX": 234.0, "minY": 108.125, "maxX": 287.0, "maxY": 142.5}, "class_id": 9, "box_caption": "cow 0.004", "scores": {"class_score": 0.0039005279541015625}, "domain": "pixel"}, {"position": {"minX": 80.5625, "minY": 68.3125, "maxX": 100.9375, "maxY": 74.1875}, "class_id": 16, "box_caption": "sheep 0.004", "scores": {"class_score": 0.0038051605224609375}, "domain": "pixel"}, {"position": {"minX": 382.75, "minY": 102.75, "maxX": 410.25, "maxY": 137.0}, "class_id": 1, "box_caption": "bicycle 0.004", "scores": {"class_score": 0.0037517547607421875}, "domain": "pixel"}, {"position": {"minX": 369.75, "minY": 105.5625, "maxX": 405.75, "maxY": 139.0}, "class_id": 16, "box_caption": "sheep 0.004", "scores": {"class_score": 0.0036640167236328125}, "domain": "pixel"}, {"position": {"minX": 380.5, "minY": 102.5, "maxX": 411.5, "maxY": 136.5}, "class_id": 10, "box_caption": "diningtable 0.003", "scores": {"class_score": 0.0034770965576171875}, "domain": "pixel"}, {"position": {"minX": 243.0, "minY": 109.875, "maxX": 278.0, "maxY": 142.125}, "class_id": 16, "box_caption": "sheep 0.003", "scores": {"class_score": 0.0034122467041015625}, "domain": "pixel"}, {"position": {"minX": 216.0, "minY": 96.4375, "maxX": 266.5, "maxY": 132.75}, "class_id": 11, "box_caption": "dog 0.003", "scores": {"class_score": 0.0034084320068359375}, "domain": "pixel"}, {"position": {"minX": 247.875, "minY": 116.875, "maxX": 285.5, "maxY": 138.625}, "class_id": 16, "box_caption": "sheep 0.003", "scores": {"class_score": 0.0033588409423828125}, "domain": "pixel"}, {"position": {"minX": 383.5, "minY": 105.625, "maxX": 413.5, "maxY": 135.125}, "class_id": 19, "box_caption": "tvmonitor 0.003", "scores": {"class_score": 0.0033473968505859375}, "domain": "pixel"}, {"position": {"minX": 51.5625, "minY": 106.375, "maxX": 71.4375, "maxY": 113.625}, "class_id": 2, "box_caption": "bird 0.003", "scores": {"class_score": 0.00330352783203125}, "domain": "pixel"}, {"position": {"minX": 51.90625, "minY": 109.625, "maxX": 76.25, "maxY": 115.875}, "class_id": 16, "box_caption": "sheep 0.003", "scores": {"class_score": 0.0032558441162109375}, "domain": "pixel"}, {"position": {"minX": 379.0, "minY": 90.5625, "maxX": 428.5, "maxY": 140.125}, "class_id": 16, "box_caption": "sheep 0.003", "scores": {"class_score": 0.0032176971435546875}, "domain": "pixel"}, {"position": {"minX": 213.25, "minY": 102.4375, "maxX": 241.25, "maxY": 133.5}, "class_id": 16, "box_caption": "sheep 0.003", "scores": {"class_score": 0.003101348876953125}, "domain": "pixel"}, {"position": {"minX": 217.5, "minY": 96.25, "maxX": 261.25, "maxY": 130.5}, "class_id": 14, "box_caption": "person 0.003", "scores": {"class_score": 0.00301361083984375}, "domain": "pixel"}, {"position": {"minX": 381.5, "minY": 97.125, "maxX": 411.5, "maxY": 138.0}, "class_id": 17, "box_caption": "sofa 0.003", "scores": {"class_score": 0.002960205078125}, "domain": "pixel"}, {"position": {"minX": 376.5, "minY": 102.6875, "maxX": 435.5, "maxY": 134.5}, "class_id": 16, "box_caption": "sheep 0.003", "scores": {"class_score": 0.0029468536376953125}, "domain": "pixel"}, {"position": {"minX": 238.875, "minY": 102.1875, "maxX": 275.0, "maxY": 138.25}, "class_id": 2, "box_caption": "bird 0.003", "scores": {"class_score": 0.002880096435546875}, "domain": "pixel"}, {"position": {"minX": 166.75, "minY": 80.875, "maxX": 326.75, "maxY": 167.375}, "class_id": 16, "box_caption": "sheep 0.003", "scores": {"class_score": 0.002574920654296875}, "domain": "pixel"}, {"position": {"minX": 231.0, "minY": 97.6875, "maxX": 269.25, "maxY": 140.75}, "class_id": 11, "box_caption": "dog 0.003", "scores": {"class_score": 0.002536773681640625}, "domain": "pixel"}, {"position": {"minX": 80.75, "minY": 66.5, "maxX": 97.5, "maxY": 76.875}, "class_id": 16, "box_caption": "sheep 0.002", "scores": {"class_score": 0.002391815185546875}, "domain": "pixel"}, {"position": {"minX": 100.5625, "minY": 179.75, "maxX": 118.8125, "maxY": 206.5}, "class_id": 16, "box_caption": "sheep 0.002", "scores": {"class_score": 0.00238037109375}, "domain": "pixel"}, {"position": {"minX": 385.0, "minY": 109.0, "maxX": 418.5, "maxY": 141.875}, "class_id": 16, "box_caption": "sheep 0.002", "scores": {"class_score": 0.0023345947265625}, "domain": "pixel"}, {"position": {"minX": 385.75, "minY": 101.3125, "maxX": 414.75, "maxY": 124.4375}, "class_id": 9, "box_caption": "cow 0.002", "scores": {"class_score": 0.0021514892578125}, "domain": "pixel"}, {"position": {"minX": 224.625, "minY": 95.75, "maxX": 297.5, "maxY": 150.25}, "class_id": 16, "box_caption": "sheep 0.002", "scores": {"class_score": 0.0020885467529296875}, "domain": "pixel"}, {"position": {"minX": 54.5625, "minY": 107.6875, "maxX": 72.625, "maxY": 115.5625}, "class_id": 16, "box_caption": "sheep 0.002", "scores": {"class_score": 0.002040863037109375}, "domain": "pixel"}, {"position": {"minX": 442.75, "minY": 137.625, "maxX": 484.25, "maxY": 154.875}, "class_id": 16, "box_caption": "sheep 0.002", "scores": {"class_score": 0.0020122528076171875}, "domain": "pixel"}, {"position": {"minX": 186.625, "minY": 68.75, "maxX": 304.5, "maxY": 155.25}, "class_id": 16, "box_caption": "sheep 0.002", "scores": {"class_score": 0.0019989013671875}, "domain": "pixel"}, {"position": {"minX": 232.25, "minY": 98.4375, "maxX": 270.5, "maxY": 140.25}, "class_id": 3, "box_caption": "boat 0.002", "scores": {"class_score": 0.0019350051879882812}, "domain": "pixel"}, {"position": {"minX": 51.5625, "minY": 106.375, "maxX": 71.4375, "maxY": 113.625}, "class_id": 14, "box_caption": "person 0.002", "scores": {"class_score": 0.0019102096557617188}, "domain": "pixel"}, {"position": {"minX": 225.75, "minY": 99.6875, "maxX": 263.75, "maxY": 136.625}, "class_id": 13, "box_caption": "motorbike 0.002", "scores": {"class_score": 0.0018596649169921875}, "domain": "pixel"}, {"position": {"minX": 75.0625, "minY": 64.4375, "maxX": 98.3125, "maxY": 72.9375}, "class_id": 16, "box_caption": "sheep 0.002", "scores": {"class_score": 0.0018520355224609375}, "domain": "pixel"}, {"position": {"minX": 229.25, "minY": 95.0, "maxX": 283.75, "maxY": 132.0}, "class_id": 16, "box_caption": "sheep 0.002", "scores": {"class_score": 0.0018157958984375}, "domain": "pixel"}, {"position": {"minX": 231.0, "minY": 97.6875, "maxX": 269.25, "maxY": 140.75}, "class_id": 15, "box_caption": "pottedplant 0.002", "scores": {"class_score": 0.0017757415771484375}, "domain": "pixel"}, {"position": {"minX": 377.75, "minY": 98.6875, "maxX": 415.75, "maxY": 130.5}, "class_id": 3, "box_caption": "boat 0.002", "scores": {"class_score": 0.0017375946044921875}, "domain": "pixel"}, {"position": {"minX": 156.25, "minY": 132.0, "maxX": 175.0, "maxY": 138.5}, "class_id": 16, "box_caption": "sheep 0.002", "scores": {"class_score": 0.0017366409301757812}, "domain": "pixel"}, {"position": {"minX": 377.75, "minY": 98.6875, "maxX": 415.75, "maxY": 130.5}, "class_id": 11, "box_caption": "dog 0.002", "scores": {"class_score": 0.0016956329345703125}, "domain": "pixel"}, {"position": {"minX": 380.25, "minY": 101.9375, "maxX": 410.25, "maxY": 142.625}, "class_id": 19, "box_caption": "tvmonitor 0.002", "scores": {"class_score": 0.0016880035400390625}, "domain": "pixel"}, {"position": {"minX": 216.625, "minY": 98.5625, "maxX": 257.0, "maxY": 129.5}, "class_id": 4, "box_caption": "bottle 0.002", "scores": {"class_score": 0.0016641616821289062}, "domain": "pixel"}, {"position": {"minX": 54.78125, "minY": 102.625, "maxX": 67.0, "maxY": 116.75}, "class_id": 9, "box_caption": "cow 0.002", "scores": {"class_score": 0.0016374588012695312}, "domain": "pixel"}, {"position": {"minX": 227.125, "minY": 98.875, "maxX": 265.5, "maxY": 138.25}, "class_id": 9, "box_caption": "cow 0.002", "scores": {"class_score": 0.0015716552734375}, "domain": "pixel"}, {"position": {"minX": 327.75, "minY": 157.875, "maxX": 348.75, "maxY": 175.125}, "class_id": 16, "box_caption": "sheep 0.002", "scores": {"class_score": 0.0015659332275390625}, "domain": "pixel"}, {"position": {"minX": 384.0, "minY": 90.375, "maxX": 412.5, "maxY": 119.5}, "class_id": 16, "box_caption": "sheep 0.002", "scores": {"class_score": 0.0015268325805664062}, "domain": "pixel"}, {"position": {"minX": 325.25, "minY": 154.875, "maxX": 352.25, "maxY": 169.625}, "class_id": 9, "box_caption": "cow 0.001", "scores": {"class_score": 0.00147247314453125}, "domain": "pixel"}, {"position": {"minX": 218.125, "minY": 99.8125, "maxX": 248.875, "maxY": 130.875}, "class_id": 2, "box_caption": "bird 0.001", "scores": {"class_score": 0.0014600753784179688}, "domain": "pixel"}, {"position": {"minX": 54.5625, "minY": 107.125, "maxX": 71.1875, "maxY": 117.375}, "class_id": 9, "box_caption": "cow 0.001", "scores": {"class_score": 0.00145721435546875}, "domain": "pixel"}, {"position": {"minX": 386.75, "minY": 112.25, "maxX": 415.75, "maxY": 139.625}, "class_id": 9, "box_caption": "cow 0.001", "scores": {"class_score": 0.0014333724975585938}, "domain": "pixel"}, {"position": {"minX": 82.5, "minY": 67.0, "maxX": 97.375, "maxY": 74.125}, "class_id": 9, "box_caption": "cow 0.001", "scores": {"class_score": 0.0014314651489257812}, "domain": "pixel"}, {"position": {"minX": 231.0, "minY": 97.6875, "maxX": 269.25, "maxY": 140.75}, "class_id": 19, "box_caption": "tvmonitor 0.001", "scores": {"class_score": 0.0013475418090820312}, "domain": "pixel"}, {"position": {"minX": 51.5625, "minY": 106.375, "maxX": 71.4375, "maxY": 113.625}, "class_id": 4, "box_caption": "bottle 0.001", "scores": {"class_score": 0.0013427734375}, "domain": "pixel"}, {"position": {"minX": 221.625, "minY": 94.9375, "maxX": 258.5, "maxY": 131.5}, "class_id": 5, "box_caption": "bus 0.001", "scores": {"class_score": 0.0013246536254882812}, "domain": "pixel"}, {"position": {"minX": 51.90625, "minY": 102.375, "maxX": 71.875, "maxY": 118.625}, "class_id": 16, "box_caption": "sheep 0.001", "scores": {"class_score": 0.0013189315795898438}, "domain": "pixel"}, {"position": {"minX": 369.75, "minY": 105.5625, "maxX": 405.75, "maxY": 139.0}, "class_id": 9, "box_caption": "cow 0.001", "scores": {"class_score": 0.0013141632080078125}, "domain": "pixel"}, {"position": {"minX": 53.5, "minY": 109.125, "maxX": 69.5, "maxY": 114.625}, "class_id": 2, "box_caption": "bird 0.001", "scores": {"class_score": 0.00130462646484375}, "domain": "pixel"}, {"position": {"minX": 365.0, "minY": 95.125, "maxX": 409.0, "maxY": 142.375}, "class_id": 16, "box_caption": "sheep 0.001", "scores": {"class_score": 0.001293182373046875}, "domain": "pixel"}, {"position": {"minX": 383.5, "minY": 116.0625, "maxX": 408.5, "maxY": 135.5}, "class_id": 14, "box_caption": "person 0.001", "scores": {"class_score": 0.00128936767578125}, "domain": "pixel"}, {"position": {"minX": 384.5, "minY": 100.0625, "maxX": 411.0, "maxY": 127.1875}, "class_id": 5, "box_caption": "bus 0.001", "scores": {"class_score": 0.0012750625610351562}, "domain": "pixel"}, {"position": {"minX": 213.75, "minY": 90.625, "maxX": 291.0, "maxY": 136.75}, "class_id": 3, "box_caption": "boat 0.001", "scores": {"class_score": 0.0012712478637695312}, "domain": "pixel"}, {"position": {"minX": 216.0, "minY": 96.4375, "maxX": 266.5, "maxY": 132.75}, "class_id": 3, "box_caption": "boat 0.001", "scores": {"class_score": 0.0012712478637695312}, "domain": "pixel"}, {"position": {"minX": 246.5, "minY": 102.8125, "maxX": 281.0, "maxY": 133.5}, "class_id": 16, "box_caption": "sheep 0.001", "scores": {"class_score": 0.0012521743774414062}, "domain": "pixel"}, {"position": {"minX": 211.375, "minY": 104.375, "maxX": 284.75, "maxY": 146.0}, "class_id": 9, "box_caption": "cow 0.001", "scores": {"class_score": 0.0012426376342773438}, "domain": "pixel"}, {"position": {"minX": 77.5625, "minY": 66.25, "maxX": 95.4375, "maxY": 73.875}, "class_id": 9, "box_caption": "cow 0.001", "scores": {"class_score": 0.0012369155883789062}, "domain": "pixel"}, {"position": {"minX": 53.5, "minY": 109.125, "maxX": 69.5, "maxY": 114.625}, "class_id": 4, "box_caption": "bottle 0.001", "scores": {"class_score": 0.0012292861938476562}, "domain": "pixel"}, {"position": {"minX": 51.90625, "minY": 102.375, "maxX": 71.875, "maxY": 118.625}, "class_id": 9, "box_caption": "cow 0.001", "scores": {"class_score": 0.001224517822265625}, "domain": "pixel"}, {"position": {"minX": 380.25, "minY": 101.9375, "maxX": 410.25, "maxY": 142.625}, "class_id": 15, "box_caption": "pottedplant 0.001", "scores": {"class_score": 0.0012216567993164062}, "domain": "pixel"}, {"position": {"minX": 46.75, "minY": 108.0, "maxX": 69.625, "maxY": 117.75}, "class_id": 16, "box_caption": "sheep 0.001", "scores": {"class_score": 0.00121307373046875}, "domain": "pixel"}, {"position": {"minX": 238.875, "minY": 102.1875, "maxX": 275.0, "maxY": 138.25}, "class_id": 9, "box_caption": "cow 0.001", "scores": {"class_score": 0.0011577606201171875}, "domain": "pixel"}, {"position": {"minX": 53.34375, "minY": 104.125, "maxX": 68.5, "maxY": 115.375}, "class_id": 14, "box_caption": "person 0.001", "scores": {"class_score": 0.0011568069458007812}, "domain": "pixel"}, {"position": {"minX": 382.0, "minY": 101.0625, "maxX": 413.0, "maxY": 126.1875}, "class_id": 2, "box_caption": "bird 0.001", "scores": {"class_score": 0.0011491775512695312}, "domain": "pixel"}, {"position": {"minX": 100.375, "minY": 186.375, "maxX": 119.375, "maxY": 200.125}, "class_id": 16, "box_caption": "sheep 0.001", "scores": {"class_score": 0.0011091232299804688}, "domain": "pixel"}, {"position": {"minX": 216.0, "minY": 96.4375, "maxX": 266.5, "maxY": 132.75}, "class_id": 17, "box_caption": "sofa 0.001", "scores": {"class_score": 0.0010938644409179688}, "domain": "pixel"}, {"position": {"minX": 238.875, "minY": 102.1875, "maxX": 275.0, "maxY": 138.25}, "class_id": 11, "box_caption": "dog 0.001", "scores": {"class_score": 0.0010862350463867188}, "domain": "pixel"}, {"position": {"minX": 227.125, "minY": 98.875, "maxX": 265.5, "maxY": 138.25}, "class_id": 14, "box_caption": "person 0.001", "scores": {"class_score": 0.00107574462890625}, "domain": "pixel"}, {"position": {"minX": 377.75, "minY": 98.6875, "maxX": 415.75, "maxY": 130.5}, "class_id": 14, "box_caption": "person 0.001", "scores": {"class_score": 0.0010728836059570312}, "domain": "pixel"}, {"position": {"minX": 216.625, "minY": 98.5625, "maxX": 257.0, "maxY": 129.5}, "class_id": 7, "box_caption": "cat 0.001", "scores": {"class_score": 0.0010538101196289062}, "domain": "pixel"}, {"position": {"minX": 53.5, "minY": 109.125, "maxX": 69.5, "maxY": 114.625}, "class_id": 9, "box_caption": "cow 0.001", "scores": {"class_score": 0.0010471343994140625}, "domain": "pixel"}, {"position": {"minX": 213.75, "minY": 90.625, "maxX": 291.0, "maxY": 136.75}, "class_id": 11, "box_caption": "dog 0.001", "scores": {"class_score": 0.0010156631469726562}, "domain": "pixel"}, {"position": {"minX": 222.0, "minY": 99.375, "maxX": 257.0, "maxY": 131.375}, "class_id": 15, "box_caption": "pottedplant 0.001", "scores": {"class_score": 0.001010894775390625}, "domain": "pixel"}], "class_labels": {"0": "aeroplane", "1": "bicycle", "2": "bird", "3": "boat", "4": "bottle", "5": "bus", "6": "car", "7": "cat", "8": "chair", "9": "cow", "10": "diningtable", "11": "dog", "12": "horse", "13": "motorbike", "14": "person", "15": "pottedplant", "16": "sheep", "17": "sofa", "18": "train", "19": "tvmonitor"}}